seamm_util/__init__.py
seamm_util/_version.py
seamm_util/argument_parser.py
seamm_util/check_executable.py
seamm_util/compact_json_encoder.py
seamm_util/configuration.py
seamm_util/dictionary.py
seamm_util/elemental_data.py
seamm_util/include_open.py
seamm_util/list_definition.py
seamm_util/md_statistics.py
seamm_util/output.py
seamm_util/plotting.py
seamm_util/printing.py
seamm_util/seamm_file.py
seamm_util/seamm_json.py
seamm_util/seamm_util.py
seamm_util/units.py
seamm_util/variable_names.py
seamm_util/water_models.py
seamm_util/zenodo.py
seamm_util-2025.9.10.dist-info/licenses/AUTHORS.rst
seamm_util-2025.9.10.dist-info/licenses/LICENSE
seamm_util-2025.9.10.dist-info/METADATA
seamm_util-2025.9.10.dist-info/WHEEL
seamm_util-2025.9.10.dist-info/top_level.txt
seamm_util-2025.9.10.dist-info/RECORD
